Metadata-Version: 1.1
Name: pysize
Version: 0.1
Summary: PySize is a lightweight tool for converting quantities between defined units
Home-page: https://benjiyamin.github.io/pysize
Author: benjiyamin, see AUTHORS.md
Author-email: benjiyamin@gmail.com
License: GNU General Public License v3 (GPLv3), see LICENSE.md
Keywords: units measurement conversion size
Platform: UNKNOWN
Classifier: Development Status :: 4 - Beta
Classifier: Operating System :: MacOS :: MacOS X
Classifier: Operating System :: Microsoft :: Windows
Classifier: Operating System :: POSIX
Classifier: License :: OSI Approved :: GNU General Public License v3 (GPLv3)
Classifier: Programming Language :: Python
